shp2metric/__init__.py
shp2metric/main.py
shp2metric-1.3.4.dist-info/entry_points.txt
shp2metric-1.3.4.dist-info/LICENSE
shp2metric-1.3.4.dist-info/METADATA
shp2metric-1.3.4.dist-info/WHEEL
shp2metric-1.3.4.dist-info/RECORD
